iscc_cli/__init__.py
iscc_cli/audio_id.py
iscc_cli/cli.py
iscc_cli/commands/__init__.py
iscc_cli/commands/batch.py
iscc_cli/commands/dump.py
iscc_cli/commands/gen.py
iscc_cli/commands/info.py
iscc_cli/commands/init.py
iscc_cli/commands/sim.py
iscc_cli/commands/test.py
iscc_cli/commands/web.py
iscc_cli/const.py
iscc_cli/datatypes.py
iscc_cli/ffmpeg.py
iscc_cli/fpcalc.py
iscc_cli/lib.py
iscc_cli/mediatype.py
iscc_cli/tika/__init__.py
iscc_cli/tika/config.py
iscc_cli/tika/detector.py
iscc_cli/tika/language.py
iscc_cli/tika/parser.py
iscc_cli/tika/tika.py
iscc_cli/tika/translate.py
iscc_cli/tika/unpack.py
iscc_cli/uread.py
iscc_cli/utils.py
iscc_cli/video_id.py
iscc_cli-0.9.12.dist-info/entry_points.txt
iscc_cli-0.9.12.dist-info/LICENSE
iscc_cli-0.9.12.dist-info/WHEEL
iscc_cli-0.9.12.dist-info/METADATA
iscc_cli-0.9.12.dist-info/RECORD
