Metadata-Version: 2.1
Name: iscc-cli
Version: 0.9.12
Summary: ISCC CLI - Creates ISCC Codes from Media Files
Home-page: https://iscc.codes/
License: MIT
Keywords: iscc,media,identifier,blockchain,cli,generator
Author: Titusz Pan
Author-email: tp@py7.de
Requires-Python: >=3.6,<4.0
Classifier: Development Status :: 4 - Beta
Classifier: Environment :: Console
Classifier: Intended Audience :: Developers
Classifier: Intended Audience :: Information Technology
Classifier: License :: OSI Approved :: MIT License
Classifier: Operating System :: Microsoft :: Windows
Classifier: Operating System :: POSIX
Classifier: Operating System :: Unix
Classifier: Programming Language :: Python
Classifier: Programming Language :: Python :: 3
Classifier: Programming Language :: Python :: 3.6
Classifier: Programming Language :: Python :: 3.7
Classifier: Programming Language :: Python :: 3.8
Classifier: Programming Language :: Python :: 3.9
Classifier: Topic :: Multimedia
Classifier: Topic :: Software Development
Classifier: Topic :: System :: Archiving
Classifier: Topic :: Utilities
Requires-Dist: click (>=7.0,<8.0)
Requires-Dist: click-default-group (>=1.2,<2.0)
Requires-Dist: colorama (>=0.4,<0.5)
Requires-Dist: imageio-ffmpeg (>=0.4,<0.5)
Requires-Dist: iscc (==1.0.5)
Requires-Dist: lxml (>=4.4,<5.0)
Requires-Dist: mobi (>=0,<1)
Requires-Dist: python-magic (>=0.4.22,<0.5.0); sys_platform == "linux"
Requires-Dist: python-magic-bin (>=0.4.14,<0.5.0); sys_platform == "win32" or sys_platform == "darwin"
Requires-Dist: requests (>=2.23.0,<3.0.0)
Project-URL: Repository, https://github.com/iscc/iscc-cli
